setup.py
geist/__init__.py
geist/colour.py
geist/core.py
geist/filters.py
geist/finders.py
geist/keyboard.py
geist/layoutfinders.py
geist/ocr.py
geist/pyplot.py
geist/repo.py
geist/similar_images.py
geist/test_image.py
geist/version.py
geist/vision.py
geist/visualfinders.py
geist.egg-info/PKG-INFO
geist.egg-info/SOURCES.txt
geist.egg-info/dependency_links.txt
geist.egg-info/requires.txt
geist.egg-info/top_level.txt
geist/backends/__init__.py
geist/backends/_common.py
geist/backends/_x11_common.py
geist/backends/fake.py
geist/backends/replay.py
geist/backends/windows.py
geist/backends/x11.py
geist/backends/xvfb.py