Metadata-Version: 1.1
Name: geist
Version: 1.0a13
Summary: Visual Automation Library
Home-page: https://github.com/thetestpeople/Geist
Author: Tony Simpson
Author-email: UNKNOWN
License: MIT
Platform: UNKNOWN
Classifier: Development Status :: 3 - Alpha
Classifier: Intended Audience :: Developers
Classifier: Programming Language :: Python
Classifier: Programming Language :: Python :: 2
Classifier: Programming Language :: Python :: 2.6
Classifier: Programming Language :: Python :: 2.7
